adeu/__init__.py
adeu/cli.py
adeu/diff.py
adeu/ingest.py
adeu/markup.py
adeu/models.py
adeu/redline/comments.py
adeu/redline/engine.py
adeu/redline/mapper.py
adeu/server.py
adeu/utils/docx.py
adeu-0.6.1.dist-info/METADATA
adeu-0.6.1.dist-info/WHEEL
adeu-0.6.1.dist-info/entry_points.txt
adeu-0.6.1.dist-info/licenses/LICENSE
adeu-0.6.1.dist-info/RECORD
