Metadata-Version: 2.4
Name: adeu
Version: 0.6.1
Summary: Automated DOCX Redlining Engine
License-File: LICENSE
Author: Mikko Korpela
Requires-Python: >=3.12
Classifier: Programming Language :: Python :: 3
Classifier: Programming Language :: Python :: 3.12
Classifier: Programming Language :: Python :: 3.13
Classifier: Programming Language :: Python :: 3.14
Requires-Dist: diff-match-patch (>=20230430)
Requires-Dist: lxml (>=5.0.0)
Requires-Dist: mcp (>=1.2.0)
Requires-Dist: pydantic (>=2.0.0)
Requires-Dist: python-docx (>=1.1.0)
Requires-Dist: structlog (>=24.0.0)
